{
  "bucket": "code-map",
  "citations": [
    {
      "citation_id": "claim-1",
      "item_keys": [
        "ai-scientist:code_location:2d6ee793a6095f17"
      ],
      "kind": "synthesized_claim",
      "label": "claim-1",
      "provenance_refs": [
        {
          "end_event_id": "019d837d-d249-71c3-9637-b8d6992ce805:2609",
          "end_line_no": 2609,
          "end_timestamp": "2026-04-13T03:19:52.486Z",
          "rule_ids": [
            "code_location.detected"
          ],
          "segment_id": "019d837d-d249-71c3-9637-b8d6992ce805:532",
          "session_id": "019d837d-d249-71c3-9637-b8d6992ce805",
          "source_id": "019d837d-d249-71c3-9637-b8d6992ce805",
          "start_event_id": "019d837d-d249-71c3-9637-b8d6992ce805:2609",
          "start_line_no": 2609,
          "start_timestamp": "2026-04-13T03:19:52.486Z",
          "statement": "- `bootstrap/projects/ai-scientist.md`"
        },
        {
          "end_event_id": "019d837d-d249-71c3-9637-b8d6992ce805:2613",
          "end_line_no": 2613,
          "end_timestamp": "2026-04-13T03:27:02.701Z",
          "rule_ids": [
            "code_location.detected"
          ],
          "segment_id": "019d837d-d249-71c3-9637-b8d6992ce805:533",
          "session_id": "019d837d-d249-71c3-9637-b8d6992ce805",
          "source_id": "019d837d-d249-71c3-9637-b8d6992ce805",
          "start_event_id": "019d837d-d249-71c3-9637-b8d6992ce805:2610",
          "start_line_no": 2610,
          "start_timestamp": "2026-04-13T03:19:52.486Z",
          "statement": "- `bootstrap/projects/ai-scientist.md`"
        },
        {
          "end_event_id": "019d837d-d249-71c3-9637-b8d6992ce805:2638",
          "end_line_no": 2638,
          "end_timestamp": "2026-04-13T03:31:01.784Z",
          "rule_ids": [
            "code_location.detected"
          ],
          "segment_id": "019d837d-d249-71c3-9637-b8d6992ce805:540",
          "session_id": "019d837d-d249-71c3-9637-b8d6992ce805",
          "source_id": "019d837d-d249-71c3-9637-b8d6992ce805",
          "start_event_id": "019d837d-d249-71c3-9637-b8d6992ce805:2635",
          "start_line_no": 2635,
          "start_timestamp": "2026-04-13T03:28:43.251Z",
          "statement": "- `bootstrap/projects/ai-scientist.md`"
        }
      ]
    },
    {
      "citation_id": "claim-2",
      "item_keys": [
        "ai-scientist:code_location:2d6ee793a6095f17"
      ],
      "kind": "synthesized_claim",
      "label": "claim-2",
      "provenance_refs": [
        {
          "end_event_id": "019d837d-d249-71c3-9637-b8d6992ce805:2609",
          "end_line_no": 2609,
          "end_timestamp": "2026-04-13T03:19:52.486Z",
          "rule_ids": [
            "code_location.detected"
          ],
          "segment_id": "019d837d-d249-71c3-9637-b8d6992ce805:532",
          "session_id": "019d837d-d249-71c3-9637-b8d6992ce805",
          "source_id": "019d837d-d249-71c3-9637-b8d6992ce805",
          "start_event_id": "019d837d-d249-71c3-9637-b8d6992ce805:2609",
          "start_line_no": 2609,
          "start_timestamp": "2026-04-13T03:19:52.486Z",
          "statement": "- `bootstrap/projects/ai-scientist.md`"
        },
        {
          "end_event_id": "019d837d-d249-71c3-9637-b8d6992ce805:2613",
          "end_line_no": 2613,
          "end_timestamp": "2026-04-13T03:27:02.701Z",
          "rule_ids": [
            "code_location.detected"
          ],
          "segment_id": "019d837d-d249-71c3-9637-b8d6992ce805:533",
          "session_id": "019d837d-d249-71c3-9637-b8d6992ce805",
          "source_id": "019d837d-d249-71c3-9637-b8d6992ce805",
          "start_event_id": "019d837d-d249-71c3-9637-b8d6992ce805:2610",
          "start_line_no": 2610,
          "start_timestamp": "2026-04-13T03:19:52.486Z",
          "statement": "- `bootstrap/projects/ai-scientist.md`"
        },
        {
          "end_event_id": "019d837d-d249-71c3-9637-b8d6992ce805:2638",
          "end_line_no": 2638,
          "end_timestamp": "2026-04-13T03:31:01.784Z",
          "rule_ids": [
            "code_location.detected"
          ],
          "segment_id": "019d837d-d249-71c3-9637-b8d6992ce805:540",
          "session_id": "019d837d-d249-71c3-9637-b8d6992ce805",
          "source_id": "019d837d-d249-71c3-9637-b8d6992ce805",
          "start_event_id": "019d837d-d249-71c3-9637-b8d6992ce805:2635",
          "start_line_no": 2635,
          "start_timestamp": "2026-04-13T03:28:43.251Z",
          "statement": "- `bootstrap/projects/ai-scientist.md`"
        }
      ]
    },
    {
      "citation_id": "item-code_location-1",
      "item_keys": [
        "ai-scientist:code_location:2d6ee793a6095f17"
      ],
      "kind": "deterministic_item",
      "label": "item-code_location-1",
      "provenance_refs": [
        {
          "end_event_id": "019d837d-d249-71c3-9637-b8d6992ce805:2609",
          "end_line_no": 2609,
          "end_timestamp": "2026-04-13T03:19:52.486Z",
          "rule_ids": [
            "code_location.detected"
          ],
          "segment_id": "019d837d-d249-71c3-9637-b8d6992ce805:532",
          "session_id": "019d837d-d249-71c3-9637-b8d6992ce805",
          "source_id": "019d837d-d249-71c3-9637-b8d6992ce805",
          "start_event_id": "019d837d-d249-71c3-9637-b8d6992ce805:2609",
          "start_line_no": 2609,
          "start_timestamp": "2026-04-13T03:19:52.486Z",
          "statement": "- `bootstrap/projects/ai-scientist.md`"
        },
        {
          "end_event_id": "019d837d-d249-71c3-9637-b8d6992ce805:2613",
          "end_line_no": 2613,
          "end_timestamp": "2026-04-13T03:27:02.701Z",
          "rule_ids": [
            "code_location.detected"
          ],
          "segment_id": "019d837d-d249-71c3-9637-b8d6992ce805:533",
          "session_id": "019d837d-d249-71c3-9637-b8d6992ce805",
          "source_id": "019d837d-d249-71c3-9637-b8d6992ce805",
          "start_event_id": "019d837d-d249-71c3-9637-b8d6992ce805:2610",
          "start_line_no": 2610,
          "start_timestamp": "2026-04-13T03:19:52.486Z",
          "statement": "- `bootstrap/projects/ai-scientist.md`"
        },
        {
          "end_event_id": "019d837d-d249-71c3-9637-b8d6992ce805:2638",
          "end_line_no": 2638,
          "end_timestamp": "2026-04-13T03:31:01.784Z",
          "rule_ids": [
            "code_location.detected"
          ],
          "segment_id": "019d837d-d249-71c3-9637-b8d6992ce805:540",
          "session_id": "019d837d-d249-71c3-9637-b8d6992ce805",
          "source_id": "019d837d-d249-71c3-9637-b8d6992ce805",
          "start_event_id": "019d837d-d249-71c3-9637-b8d6992ce805:2635",
          "start_line_no": 2635,
          "start_timestamp": "2026-04-13T03:28:43.251Z",
          "statement": "- `bootstrap/projects/ai-scientist.md`"
        }
      ]
    }
  ],
  "domain": "ai-scientist",
  "input_item_keys": [
    "ai-scientist:code_location:2d6ee793a6095f17"
  ],
  "page_id": "projects/ai-scientist/code-map",
  "page_type": "bucket_page",
  "rendered_page_metadata": {
    "claim_count": 2,
    "conflict_count": 0,
    "related_domains": [
      "global"
    ],
    "related_pages": [
      {
        "page_key": "index",
        "title": "AI Scientist",
        "wikilink": "[[projects/ai-scientist/index|AI Scientist]]"
      },
      {
        "page_key": "communication-preferences",
        "title": "AI Scientist - Communication Preferences",
        "wikilink": "[[projects/ai-scientist/communication-preferences|AI Scientist - Communication Preferences]]"
      },
      {
        "page_key": "workflow-rules",
        "title": "AI Scientist - Workflow Rules",
        "wikilink": "[[projects/ai-scientist/workflow-rules|AI Scientist - Workflow Rules]]"
      },
      {
        "page_key": "architecture",
        "title": "AI Scientist - Architecture",
        "wikilink": "[[projects/ai-scientist/architecture|AI Scientist - Architecture]]"
      },
      {
        "page_key": "current-state",
        "title": "AI Scientist - Current State",
        "wikilink": "[[projects/ai-scientist/current-state|AI Scientist - Current State]]"
      },
      {
        "page_key": "tasks",
        "title": "AI Scientist - Tasks",
        "wikilink": "[[projects/ai-scientist/tasks|AI Scientist - Tasks]]"
      },
      {
        "page_key": "outcomes",
        "title": "AI Scientist - Outcomes",
        "wikilink": "[[projects/ai-scientist/outcomes|AI Scientist - Outcomes]]"
      },
      {
        "page_key": "failures",
        "title": "AI Scientist - Failures",
        "wikilink": "[[projects/ai-scientist/failures|AI Scientist - Failures]]"
      },
      {
        "page_key": "decisions",
        "title": "AI Scientist - Decisions",
        "wikilink": "[[projects/ai-scientist/decisions|AI Scientist - Decisions]]"
      },
      {
        "page_key": "next-steps",
        "title": "AI Scientist - Next Steps",
        "wikilink": "[[projects/ai-scientist/next-steps|AI Scientist - Next Steps]]"
      },
      {
        "page_key": "open-questions",
        "title": "AI Scientist - Open Questions",
        "wikilink": "[[projects/ai-scientist/open-questions|AI Scientist - Open Questions]]"
      }
    ],
    "relative_page_path": "projects/ai-scientist/code-map.md",
    "source_count": 1,
    "title": "AI Scientist - Code Map"
  },
  "renderer": "obsidian_markdown",
  "synthesized_claims": [
    {
      "claim_id": "claim-1",
      "confidence": "strong",
      "latent_type": "codebase_map_abstractions",
      "provenance_refs": [
        {
          "end_event_id": "019d837d-d249-71c3-9637-b8d6992ce805:2609",
          "end_line_no": 2609,
          "end_timestamp": "2026-04-13T03:19:52.486Z",
          "rule_ids": [
            "code_location.detected"
          ],
          "segment_id": "019d837d-d249-71c3-9637-b8d6992ce805:532",
          "session_id": "019d837d-d249-71c3-9637-b8d6992ce805",
          "source_id": "019d837d-d249-71c3-9637-b8d6992ce805",
          "start_event_id": "019d837d-d249-71c3-9637-b8d6992ce805:2609",
          "start_line_no": 2609,
          "start_timestamp": "2026-04-13T03:19:52.486Z",
          "statement": "- `bootstrap/projects/ai-scientist.md`"
        },
        {
          "end_event_id": "019d837d-d249-71c3-9637-b8d6992ce805:2613",
          "end_line_no": 2613,
          "end_timestamp": "2026-04-13T03:27:02.701Z",
          "rule_ids": [
            "code_location.detected"
          ],
          "segment_id": "019d837d-d249-71c3-9637-b8d6992ce805:533",
          "session_id": "019d837d-d249-71c3-9637-b8d6992ce805",
          "source_id": "019d837d-d249-71c3-9637-b8d6992ce805",
          "start_event_id": "019d837d-d249-71c3-9637-b8d6992ce805:2610",
          "start_line_no": 2610,
          "start_timestamp": "2026-04-13T03:19:52.486Z",
          "statement": "- `bootstrap/projects/ai-scientist.md`"
        },
        {
          "end_event_id": "019d837d-d249-71c3-9637-b8d6992ce805:2638",
          "end_line_no": 2638,
          "end_timestamp": "2026-04-13T03:31:01.784Z",
          "rule_ids": [
            "code_location.detected"
          ],
          "segment_id": "019d837d-d249-71c3-9637-b8d6992ce805:540",
          "session_id": "019d837d-d249-71c3-9637-b8d6992ce805",
          "source_id": "019d837d-d249-71c3-9637-b8d6992ce805",
          "start_event_id": "019d837d-d249-71c3-9637-b8d6992ce805:2635",
          "start_line_no": 2635,
          "start_timestamp": "2026-04-13T03:28:43.251Z",
          "statement": "- `bootstrap/projects/ai-scientist.md`"
        }
      ],
      "section_id": "summary",
      "supporting_item_ids": [
        "ai-scientist:code_location:2d6ee793a6095f17"
      ],
      "text": "The code for the AI Scientist project is located in `bootstrap/projects/ai-scientist.md`."
    },
    {
      "claim_id": "claim-2",
      "confidence": "strong",
      "latent_type": "codebase_map_abstractions",
      "provenance_refs": [
        {
          "end_event_id": "019d837d-d249-71c3-9637-b8d6992ce805:2609",
          "end_line_no": 2609,
          "end_timestamp": "2026-04-13T03:19:52.486Z",
          "rule_ids": [
            "code_location.detected"
          ],
          "segment_id": "019d837d-d249-71c3-9637-b8d6992ce805:532",
          "session_id": "019d837d-d249-71c3-9637-b8d6992ce805",
          "source_id": "019d837d-d249-71c3-9637-b8d6992ce805",
          "start_event_id": "019d837d-d249-71c3-9637-b8d6992ce805:2609",
          "start_line_no": 2609,
          "start_timestamp": "2026-04-13T03:19:52.486Z",
          "statement": "- `bootstrap/projects/ai-scientist.md`"
        },
        {
          "end_event_id": "019d837d-d249-71c3-9637-b8d6992ce805:2613",
          "end_line_no": 2613,
          "end_timestamp": "2026-04-13T03:27:02.701Z",
          "rule_ids": [
            "code_location.detected"
          ],
          "segment_id": "019d837d-d249-71c3-9637-b8d6992ce805:533",
          "session_id": "019d837d-d249-71c3-9637-b8d6992ce805",
          "source_id": "019d837d-d249-71c3-9637-b8d6992ce805",
          "start_event_id": "019d837d-d249-71c3-9637-b8d6992ce805:2610",
          "start_line_no": 2610,
          "start_timestamp": "2026-04-13T03:19:52.486Z",
          "statement": "- `bootstrap/projects/ai-scientist.md`"
        },
        {
          "end_event_id": "019d837d-d249-71c3-9637-b8d6992ce805:2638",
          "end_line_no": 2638,
          "end_timestamp": "2026-04-13T03:31:01.784Z",
          "rule_ids": [
            "code_location.detected"
          ],
          "segment_id": "019d837d-d249-71c3-9637-b8d6992ce805:540",
          "session_id": "019d837d-d249-71c3-9637-b8d6992ce805",
          "source_id": "019d837d-d249-71c3-9637-b8d6992ce805",
          "start_event_id": "019d837d-d249-71c3-9637-b8d6992ce805:2635",
          "start_line_no": 2635,
          "start_timestamp": "2026-04-13T03:28:43.251Z",
          "statement": "- `bootstrap/projects/ai-scientist.md`"
        }
      ],
      "section_id": "code_location",
      "supporting_item_ids": [
        "ai-scientist:code_location:2d6ee793a6095f17"
      ],
      "text": "The code for the AI Scientist project is located in `bootstrap/projects/ai-scientist.md`."
    }
  ],
  "versions": {
    "page_config_version": 2,
    "renderer_version": 2,
    "synthesis_prompt_version": 2,
    "synthesis_schema_version": 1,
    "wiki_schema_version": 2
  }
}
